oacmpy/Attitude.py
oacmpy/CelestialBody.py
oacmpy/State.py
oacmpy/__init__.py
oacmpy/__main__.py
oacmpy/constants.py
oacmpy/errors.py
oacmpy/oem2czml.py
oacmpy/ccsds/AbstractDataMessage.py
oacmpy/ccsds/Aem.py
oacmpy/ccsds/Apm.py
oacmpy/ccsds/Cdm.py
oacmpy/ccsds/CommonEphemerisData.py
oacmpy/ccsds/CommonMetadataParser.py
oacmpy/ccsds/CommonOrbitData.py
oacmpy/ccsds/CovarianceParameters.py
oacmpy/ccsds/DataParserUtils.py
oacmpy/ccsds/Oem.py
oacmpy/ccsds/Omm.py
oacmpy/ccsds/Opm.py
oacmpy/ccsds/OrbitParameters.py
oacmpy/ccsds/__init__.py
oacmpy/ccsds/enumerates.py
oacmpy/ccsds/exceptions.py
oacmpy/ccsds/units.py
oacmpy/czml/CdmToCzml.py
oacmpy/czml/CzmlUtils.py
oacmpy/czml/OemToCzml.py
oacmpy/czml/ScenarioCzml.py
oacmpy/czml/__init__.py
oacmpy/data/finals.all
oacmpy/data/finals2000A.all
oacmpy/data/tai-utc.dat
oacmpy/data/1996/tab5.1.txt
oacmpy/data/2004/tab5.2a.txt
oacmpy/data/2004/tab5.2b.txt
oacmpy/data/2004/tab5.2c.txt
oacmpy/data/2006/tab5.3a.txt
oacmpy/data/2006/tab5.3b.txt
oacmpy/data/2010/tab5.1a.txt
oacmpy/data/2010/tab5.2a.txt
oacmpy/data/2010/tab5.2b.txt
oacmpy/data/2010/tab5.2d.txt
oacmpy/datetime/Date.py
oacmpy/datetime/TaiUtc.py
oacmpy/datetime/TimeScale.py
oacmpy/datetime/__init__.py
oacmpy/frames/AbstractFrame.py
oacmpy/frames/__init__.py
oacmpy/frames/frames.py
oacmpy/frames/iers/TableReader.py
oacmpy/frames/iers/__init__.py
oacmpy/frames/iers/eop.py
oacmpy/frames/iers/iau1980.py
oacmpy/frames/iers/iau2000.py
oacmpy/frames/iers/iau2010.py
oacmpy/frames/iers/iers.py
oacmpy/frames/iers/iers2003.py
oacmpy/utils/__init__.py
oacmpy/utils/rotation.py
oacmpy-0.0.3.dist-info/LICENSE.md
oacmpy-0.0.3.dist-info/METADATA
oacmpy-0.0.3.dist-info/WHEEL
oacmpy-0.0.3.dist-info/top_level.txt
oacmpy-0.0.3.dist-info/RECORD
