Metadata-Version: 2.1
Name: oacmpy
Version: 0.0.3
Summary: Parse CCSDS Data Message, including OEM, AEM and CDM, and convert them to a CZML scenario file.
Home-page: https://gitlab.com/jorispio/ccsds2czml
Author: Joris T. OLYMPIO
Author-email: jto.devs@gmail.com
License: MIT
Keywords: "space trajectory" orbit
Platform: UNKNOWN
Classifier: Development Status :: 4 - Beta
Classifier: Intended Audience :: Science/Research
Classifier: Topic :: Scientific/Engineering
Classifier: License :: OSI Approved :: GNU General Public License v3 (GPLv3)
Classifier: Programming Language :: Python :: 3
Classifier: Programming Language :: Python :: 3.6
Classifier: Programming Language :: Python :: 3.7
Classifier: Programming Language :: Python :: 3.8
Requires-Python: >=3.6
License-File: LICENSE.md
